mood_ring/__init__.py
mood_ring/compat.py
mood_ring/mood_ring.py
mood_ring-0.1.1.dist-info/LICENSE
mood_ring-0.1.1.dist-info/METADATA
mood_ring-0.1.1.dist-info/WHEEL
mood_ring-0.1.1.dist-info/top_level.txt
mood_ring-0.1.1.dist-info/RECORD
