Metadata-Version: 2.1
Name: mood-ring
Version: 0.1.1
Summary: Novelty mood ring object that returns a mood as a string
Home-page: https://github.com/joshah-moors/mood-ring
Author: Joshah Moors
License: UNKNOWN
Platform: UNKNOWN
Classifier: Programming Language :: Python :: 3
Classifier: License :: OSI Approved :: MIT License
Classifier: Operating System :: OS Independent
Requires-Python: >=3.5
